LICENSE
MANIFEST.in
README.rst
setup.py
alternator/__init__.py
alternator/generator.py
alternator/iter.py
alternator/reduce.py
alternator.egg-info/PKG-INFO
alternator.egg-info/SOURCES.txt
alternator.egg-info/dependency_links.txt
alternator.egg-info/top_level.txt
tests/asynchelpers.py
tests/test_alternator.py