Metadata-Version: 1.1
Name: alternator
Version: 0.1.1
Summary: Create asynchronous generators from coroutines
Home-page: https://github.com/groner/alternator.py/
Author: Kai Groner
Author-email: kai@gronr.com
License: BSD
Platform: UNKNOWN
Classifier: Development Status :: 3 - Alpha
Classifier: Intended Audience :: Developers
Classifier: Programming Language :: Python :: 3.5
